CONTRIBUTING.rst
HISTORY.rst
LICENSE
MANIFEST.in
README.rst
resources.qrc
setup.cfg
setup.py
./__init__.py
./labelImg.py
data/predefined_classes.txt
labelImgPlus.egg-info/PKG-INFO
labelImgPlus.egg-info/SOURCES.txt
labelImgPlus.egg-info/dependency_links.txt
labelImgPlus.egg-info/entry_points.txt
labelImgPlus.egg-info/not-zip-safe
labelImgPlus.egg-info/requires.txt
labelImgPlus.egg-info/top_level.txt
libs/__init__.py
libs/canvas.py
libs/coco_io.py
libs/colorDialog.py
libs/combobox.py
libs/constants.py
libs/create_ml_io.py
libs/default_label_combobox.py
libs/hashableQListWidgetItem.py
libs/labelDialog.py
libs/labelFile.py
libs/lightWidget.py
libs/pascal_voc_io.py
libs/resources.py
libs/settings.py
libs/shape.py
libs/stringBundle.py
libs/toolBar.py
libs/ustr.py
libs/utils.py
libs/yolo_io.py
libs/zoomWidget.py