Metadata-Version: 2.1
Name: labelImgPlus
Version: 1.8.10
Summary: LabelImg is a graphical image annotation tool and label object bounding boxes in images
Home-page: https://github.com/tzutalin/labelImg
Author: TzuTa Lin
Author-email: tzu.ta.lin@gmail.com
License: MIT license
Keywords: labelImg labelTool development annotation deeplearning
Classifier: Development Status :: 5 - Production/Stable
Classifier: Intended Audience :: Developers
Classifier: License :: OSI Approved :: MIT License
Classifier: Natural Language :: English
Classifier: Programming Language :: Python :: 3
Classifier: Programming Language :: Python :: 3.3
Classifier: Programming Language :: Python :: 3.4
Classifier: Programming Language :: Python :: 3.5
Classifier: Programming Language :: Python :: 3.6
Classifier: Programming Language :: Python :: 3.7
Requires-Python: >=3.0.0
License-File: LICENSE
